mypackage/__init__.py
UCS633_topsis_SulbhMahajan-1.1.3.dist-info/METADATA
UCS633_topsis_SulbhMahajan-1.1.3.dist-info/WHEEL
UCS633_topsis_SulbhMahajan-1.1.3.dist-info/entry_points.txt
UCS633_topsis_SulbhMahajan-1.1.3.dist-info/top_level.txt
UCS633_topsis_SulbhMahajan-1.1.3.dist-info/RECORD
